Workbook

Sheet Assumptions
A1: Micron Chip Shortage Model - Assumptions
A3: Metric | B3: Bear | C3: Base | D3: Bull
A4: Quarterly Volume Growth % | B4: 0.01 | C4: 0.03 | D4: 0.05
A5: Quarterly Price Growth % | B5: -0.08 | C5: 0.1 | D5: 0.2
A6: Gross Margin % | B6: 0.4 | C6: 0.65 | D6: 0.78
A10: Revenue Baseline ($M) | B10: 41460

Sheet Model
A1: Scenerio Selector | B1: Base
A3: Volume Growth % | B3: =HLOOKUP($B$1,Assumptions!$B$3:$D$6,2,FALSE) -> 0.03
A4: Price Growth % | B4: =HLOOKUP($B$1,Assumptions!$B$3:$D$6,3,FALSE) -> 0.1
A5: Gross Margin % | B5: =HLOOKUP($B$1,Assumptions!$B$3:$D$6,4,FALSE) -> 0.65
A8: Quarter | B8: Q1 | C8: Q2 | D8: Q3 | E8: Q4
A9: Volume Index | B9: =100*(1+B$3) -> 103 | C9: =B9*(1+$B$3) -> 106.09 | D9: =C9*(1+$B$3) -> 109.2727 | E9: =D9*(1+$B$3) -> 112.55088
A10: Price Index | B10: =100*(1+B$4) -> 110 | C10: =B10*(1+$B$4) -> 121 | D10: =C10*(1+$B$4) -> 133.1 | E10: =D10*(1+$B$4) -> 146.41
A11: Revenue ($M) | B11: =Assumptions!$B$10*(B9/100)*(B10/100) -> 46974.18 | C11: =B11*(C9/B9)*(C10/B10) -> 53221.746 | D11: =C11*(D9/C9)*(D10/C10) -> 60300.238 | E11: =D11*(E9/D9)*(E10/D10) -> 68320.17
A12: Gross Profit ($M) | B12: =B11*$B$5 -> 30533.217 | C12: =C11*$B$5 -> 34594.135 | D12: =D11*$B$5 -> 39195.155 | E12: =E11*$B$5 -> 44408.11
A13: Gross Margin % (check) | B13: =B12/B11 -> 0.65 | C13: =C12/C11 -> 0.65 | D13: =D12/D11 -> 0.65 | E13: =E12/E11 -> 0.65

Sheet Variance_Bridge
A1: Starting Revenue ($M) | B1: =Assumptions!$B$10 -> 41460 | C1: Baseline: Micron actual Q3 FY26 revenue (quarter ended May 28, 2026), verified.
A2: Volume Effect ($M) | B2: =B1*(Model!E9/100-1) -> 5203.5953
A3: Price Effect ($M) | B3: =B1*(Model!E9/100)*(Model!E10/100-1) -> 21656.575
A4: Ending Revenue ($M) | B4: =B1+B2+B3 -> 68320.17
A5: Check vs Model!E11 | B5: =B4-Model!E11 -> 0
A7: Bridge Component | B7: Base (hidden) | C7: Increase | D7: Total
A8: =A1 -> Starting Revenue ($M) | B8: 0 | C8: 0 | D8: =$B$1 -> 41460
A9: =A2 -> Volume Effect ($M) | B9: =$B$1 -> 41460 | C9: =$B$2 -> 5203.5953 | D9: 0
A10: =A3 -> Price Effect ($M) | B10: =$B$1+$B$2 -> 46663.595 | C10: =$B$3 -> 21656.575 | D10: 0
A11: =A4 -> Ending Revenue ($M) | B11: 0 | C11: 0 | D11: =$B$4 -> 68320.17
